apparata/__init__.py
apparata/apparata.py
apparata-0.1.1.dist-info/METADATA
apparata-0.1.1.dist-info/WHEEL
apparata-0.1.1.dist-info/top_level.txt
apparata-0.1.1.dist-info/RECORD
