Metadata-Version: 2.1
Name: apparata
Version: 0.1.1
Summary: A collection of useful functions for generating random data.
Author: Nishant Gerald
Author-email: nishantgerald@gmail.com
Requires-Dist: faker
Requires-Dist: pandas
